opentargets_validator/__init__.py
opentargets_validator/cli.py
opentargets_validator/helpers.py
opentargets_validator/validator.py
opentargets_validator/version.py
opentargets_validator/resources/logging.ini
opentargets_validator-1.0.1.dist-info/METADATA
opentargets_validator-1.0.1.dist-info/WHEEL
opentargets_validator-1.0.1.dist-info/entry_points.txt
opentargets_validator-1.0.1.dist-info/licenses/LICENSE
opentargets_validator-1.0.1.dist-info/RECORD
