Metadata-Version: 2.4
Name: opentargets-validator
Version: 1.0.1
Summary: Schema validation for evidence submitted to Open Targets
Project-URL: Homepage, https://github.com/opentargets/validator
Project-URL: Repository, https://github.com/opentargets/validator
Project-URL: Documentation, https://github.com/opentargets/validator#readme
Project-URL: Bug Tracker, https://github.com/opentargets/validator/issues
Author-email: Open Targets <data@opentargets.org>
Maintainer-email: Open Targets <data@opentargets.org>
License: Apache-2.0
License-File: LICENSE
Keywords: bioinformatics,opentargets,python3
Classifier: Development Status :: 5 - Production/Stable
Classifier: Intended Audience :: Science/Research
Classifier: License :: OSI Approved :: Apache Software License
Classifier: Operating System :: OS Independent
Classifier: Programming Language :: Python :: 3
Classifier: Programming Language :: Python :: 3.8
Classifier: Programming Language :: Python :: 3.9
Classifier: Programming Language :: Python :: 3.10
Classifier: Programming Language :: Python :: 3.11
Classifier: Programming Language :: Python :: 3.12
Classifier: Programming Language :: Python :: 3.13
Classifier: Topic :: Scientific/Engineering :: Bio-Informatics
Classifier: Topic :: Software Development :: Libraries :: Python Modules
Requires-Python: >=3.8.1
Requires-Dist: fastjsonschema>=2.18.0
Requires-Dist: pathos>=0.3.1
Provides-Extra: build
Requires-Dist: build; extra == 'build'
Requires-Dist: twine; extra == 'build'
Provides-Extra: dev
Requires-Dist: build; extra == 'dev'
Requires-Dist: codecov; extra == 'dev'
Requires-Dist: pytest; extra == 'dev'
Requires-Dist: pytest-cov; extra == 'dev'
Requires-Dist: ruff; extra == 'dev'
Requires-Dist: twine; extra == 'dev'
Requires-Dist: uv; extra == 'dev'
Provides-Extra: lint
Requires-Dist: mypy; extra == 'lint'
Requires-Dist: ruff; extra == 'lint'
Provides-Extra: test
Requires-Dist: pytest; extra == 'test'
Requires-Dist: pytest-cov; extra == 'test'
Requires-Dist: pytest-xdist; extra == 'test'
